{"_ts":[1522571601],"_r":{"breakdown":{"html":{"bytes":[3546],"requests":[1]},"js":{"bytes":[59685],"requests":[4]},"css":{"bytes":[37251],"requests":[7]},"image":{"bytes":[34059],"requests":[2]},"flash":{"bytes":[0],"requests":[0]},"font":{"bytes":[165108],"requests":[6]},"video":{"bytes":[0],"requests":[0]},"other":{"bytes":[0],"requests":[0]}},"date":[1522571601],"domElements":[140],"domInteractive":[781],"firstPaint":[694.9],"fullyLoaded":[1223],"id":["180401_A7_5d32b14ca6832d3a5a9a13339dfa3a67"],"loadTime":[1179],"render":[700],"SpeedIndex":[742],"TTFB":[165],"videoFrames":[[{"_i":"ms_000000.jpg","_t":0,"_vc":0},{"_i":"ms_000700.jpg","_t":700,"_vc":79},{"_i":"ms_000900.jpg","_t":900,"_vc":100}]],"visualComplete":[900],"lighthouse":[54],"pagespeed":[85]}}