{"_ts":[1493600631,1493643838,1493687414,1493773982,1493817114,1493860752],"_r":{"breakdown":{"html":{"bytes":[325,324,3065,3066,3065,3065],"requests":[1,1,1,1,1,1]},"js":{"bytes":[51917,51939,57226,57200,57220,57220],"requests":[4,4,4,4,4,4]},"css":{"bytes":[25444,32761,38004,38004,38003,38004],"requests":[7,7,7,7,7,7]},"image":{"bytes":[31577,31577,34036,34037,34036,34036],"requests":[2,2,2,2,2,2]},"flash":{"bytes":[0,0,0,0,0,0],"requests":[0,0,0,0,0,0]},"font":{"bytes":[116814,116814,135002,135002,135051,135001],"requests":[6,6,6,6,6,6]},"other":{"bytes":[0,0,0,0,0,0],"requests":[0,0,0,0,0,0]}},"date":[1493600631,1493643838,1493687414,1493773982,1493817114,1493860752],"domElements":[119,119,119,119,119,119],"domInteractive":[3627,3441,3572,3764,3418,5857],"firstPaint":[2999,3087,2954,3148,2990,3589],"fullyLoaded":[5057,6247,5155,6537,5243,14729],"id":["170501_8G_2SS","170501_D7_PHV","170502_AE_2ZV","170503_AW_2YC","170503_X3_TYN","170504_EC_3JT"],"loadTime":[4707,5891,4797,5048,4855,13846],"render":[2937,2983,3098,3288,3074,3697],"SpeedIndex":[3908,3918,3951,4189,3953,5549],"TTFB":[1178,1238,1325,1414,1346,1333],"videoFrames":[[{"_i":"frame_0000.jpg","_t":0,"_vc":0},{"_i":"frame_0029.jpg","_t":2900,"_vc":47},{"_i":"frame_0045.jpg","_t":4500,"_vc":60},{"_i":"frame_0049.jpg","_t":4900,"_vc":100}],[{"_i":"frame_0000.jpg","_t":0,"_vc":0},{"_i":"frame_0030.jpg","_t":3000,"_vc":46},{"_i":"frame_0046.jpg","_t":4600,"_vc":96},{"_i":"frame_0059.jpg","_t":5900,"_vc":99},{"_i":"frame_0061.jpg","_t":6100,"_vc":100}],[{"_i":"frame_0000.jpg","_t":0,"_vc":0},{"_i":"frame_0031.jpg","_t":3100,"_vc":45},{"_i":"frame_0046.jpg","_t":4600,"_vc":86},{"_i":"frame_0047.jpg","_t":4700,"_vc":96},{"_i":"frame_0050.jpg","_t":5000,"_vc":100}],[{"_i":"frame_0000.jpg","_t":0,"_vc":0},{"_i":"frame_0033.jpg","_t":3300,"_vc":45},{"_i":"frame_0048.jpg","_t":4800,"_vc":86},{"_i":"frame_0051.jpg","_t":5100,"_vc":89},{"_i":"frame_0053.jpg","_t":5300,"_vc":100}],[{"_i":"frame_0000.jpg","_t":0,"_vc":0},{"_i":"frame_0031.jpg","_t":3100,"_vc":45},{"_i":"frame_0046.jpg","_t":4600,"_vc":86},{"_i":"frame_0048.jpg","_t":4800,"_vc":100}],[{"_i":"frame_0000.jpg","_t":0,"_vc":0},{"_i":"frame_0037.jpg","_t":3700,"_vc":45},{"_i":"frame_0066.jpg","_t":6600,"_vc":96},{"_i":"frame_0127.jpg","_t":12700,"_vc":99},{"_i":"frame_0137.jpg","_t":13700,"_vc":100}]],"visualComplete":[4900,6100,5000,5300,4800,13700],"lighthouse":[null,null,null,null,null,null],"pagespeed":[85,85,85,85,85,85]}}